learnsaxs/__init__.py
learnsaxs-0.0.5.dist-info/METADATA
learnsaxs-0.0.5.dist-info/WHEEL
learnsaxs-0.0.5.dist-info/licenses/LICENSE
learnsaxs-0.0.5.dist-info/RECORD
