Metadata-Version: 2.4
Name: learnsaxs
Version: 0.0.5
Summary: Jupyter Notebook examples for SEC-SAXS learning
Project-URL: Repository, https://github.com/freesemt/learnsaxs
Author: Masatsuyo Takahashi
Maintainer: Masatsuyo Takahashi
License: MIT License
License-File: LICENSE
Keywords: SEC-SAXS
Classifier: Development Status :: 3 - Alpha
Classifier: Programming Language :: Python
Requires-Python: >=3.9
Requires-Dist: matplotlib
Requires-Dist: numpy
Requires-Dist: scipy
